richtext_typst/__init__.py
richtext_typst/base.py
richtext_typst/converter.py
richtext_typst/exceptions.py
richtext_typst/py.typed
richtext_typst/formats/outline.py
richtext_typst/formats/prosemirror.py
richtext_typst/formats/quill.py
richtext_typst/formats/slate.py
richtext_typst-0.1.2.dist-info/licenses/LICENSE
richtext_typst-0.1.2.dist-info/METADATA
richtext_typst-0.1.2.dist-info/WHEEL
richtext_typst-0.1.2.dist-info/top_level.txt
richtext_typst-0.1.2.dist-info/RECORD
