Metadata-Version: 2.4
Name: richtext-typst
Version: 0.1.2
Summary: Convert Rich Text JSON to Typst
Author-email: Bruno DI LIVIO <perruque-gruau-7k@icloud.com>
License-Expression: MIT
Project-URL: Homepage, https://github.com/Lamkateh/richtext-typst
Project-URL: Issues, https://github.com/Lamkateh/richtext-typst/issues
Requires-Python: >=3.10
License-File: LICENSE
Dynamic: license-file
